chatsky_ui/__init__.py
chatsky_ui/api/__init_.py
chatsky_ui/api/api_v1/__init__.py
chatsky_ui/api/api_v1/api.py
chatsky_ui/api/api_v1/endpoints/__init__.py
chatsky_ui/api/api_v1/endpoints/auth.py
chatsky_ui/api/api_v1/endpoints/bot.py
chatsky_ui/api/api_v1/endpoints/chatsky_services.py
chatsky_ui/api/api_v1/endpoints/config.py
chatsky_ui/api/api_v1/endpoints/flows.py
chatsky_ui/api/deps.py
chatsky_ui/cli.py
chatsky_ui/clients/__init__.py
chatsky_ui/clients/chatsky_client.py
chatsky_ui/clients/context_storage.py
chatsky_ui/clients/http_interface.py
chatsky_ui/core/__init__.py
chatsky_ui/core/auth.py
chatsky_ui/core/config.py
chatsky_ui/core/logger_config.py
chatsky_ui/core/security.py
chatsky_ui/db/__init__.py
chatsky_ui/db/base.py
chatsky_ui/initial_data.py
chatsky_ui/main.py
chatsky_ui/schemas/__init__.py
chatsky_ui/schemas/code_snippet.py
chatsky_ui/schemas/front_graph_components/base_component.py
chatsky_ui/schemas/front_graph_components/flow.py
chatsky_ui/schemas/front_graph_components/info_holders/__init__.py
chatsky_ui/schemas/front_graph_components/info_holders/condition.py
chatsky_ui/schemas/front_graph_components/info_holders/response.py
chatsky_ui/schemas/front_graph_components/messenger.py
chatsky_ui/schemas/front_graph_components/node.py
chatsky_ui/schemas/front_graph_components/pipeline.py
chatsky_ui/schemas/front_graph_components/script.py
chatsky_ui/schemas/front_graph_components/slot.py
chatsky_ui/schemas/pagination.py
chatsky_ui/schemas/preset.py
chatsky_ui/schemas/process_status.py
chatsky_ui/services/__init__.py
chatsky_ui/services/json_converter/base_converter.py
chatsky_ui/services/json_converter/consts.py
chatsky_ui/services/json_converter/flow_converter.py
chatsky_ui/services/json_converter/logic_component_converter/chatsky_condition_converter.py
chatsky_ui/services/json_converter/logic_component_converter/condition_converter.py
chatsky_ui/services/json_converter/logic_component_converter/response_converter.py
chatsky_ui-0.6.0.dist-info/METADATA
chatsky_ui-0.6.0.dist-info/WHEEL
chatsky_ui-0.6.0.dist-info/entry_points.txt
chatsky_ui-0.6.0.dist-info/RECORD
