Metadata-Version: 2.3
Name: chatsky-ui
Version: 0.6.0
Summary: Chatsky-UI is GUI for Chatsky Framework, that is a free and open-source software stack for creating chatbots, released under the terms of Apache License 2.0.
License: Apache-2.0
Keywords: chatbots
Author: Denis Kuznetsov
Author-email: kuznetsov.den.p@gmail.com
Requires-Python: >=3.9, !=2.7.*, !=3.0.*, !=3.1.*, !=3.2.*, !=3.3.*, !=3.4.*, !=3.5.*, !=3.6.*, !=3.7.*, !=3.8.*
Classifier: License :: OSI Approved :: Apache Software License
Classifier: Programming Language :: Python :: 3
Classifier: Programming Language :: Python :: 3.9
Classifier: Programming Language :: Python :: 3.10
Classifier: Programming Language :: Python :: 3.11
Classifier: Programming Language :: Python :: 3.12
Classifier: Programming Language :: Python :: 3.13
Requires-Dist: aiofiles (>=23.2.1,<24.0.0)
Requires-Dist: chatsky[sqlite,telegram,yaml] (==0.10.0)
Requires-Dist: cookiecutter (>=2.6.0,<3.0.0)
Requires-Dist: fastapi (>=0.110.0,<0.111.0)
Requires-Dist: gitpython (>=3.1.43,<4.0.0)
Requires-Dist: httpx (>=0.27.0,<0.28.0)
Requires-Dist: httpx-ws (>=0.6.0,<0.7.0)
Requires-Dist: omegaconf (>=2.3.0,<3.0.0)
Requires-Dist: pydantic (>=2.6.3,<3.0.0)
Requires-Dist: pydantic-settings (>=2.2.1,<3.0.0)
Requires-Dist: pylint (>=3.2.3,<4.0.0)
Requires-Dist: typer (>=0.9.0,<0.10.0)
Requires-Dist: uvicorn[standard] (>=0.28.0,<0.29.0)
Project-URL: Homepage, https://github.com/deeppavlov/chatsky-ui
